{
	"labels": ["January", "February", "March"],
	"datasets": [
		{ "label": "Dataset 0", "data": [96, 2, 5] },
		{ "label": "Dataset 1", "data": [45, 92, 2] },
		{ "label": "Dataset 2", "data": [80, 87, 98] },
		{ "label": "Dataset 3", "data": [4, 25, 73] },
		{ "label": "Dataset 4", "data": [22, 9, 32] },
		{ "label": "Dataset 5", "data": [63, 43, 92] },
		{ "label": "Dataset 6", "data": [28, 83, 38] },
		{ "label": "Dataset 7", "data": [57, 14, 27] },
		{ "label": "Dataset 8", "data": [82, 32, 48] },
		{ "label": "Dataset 9", "data": [86, 55, 95] },
		{ "label": "Dataset 10", "data": [89, 66, 91] },
		{ "label": "Dataset 11", "data": [45, 87, 29] },
		{ "label": "Dataset 12", "data": [77, 73, 100] },
		{ "label": "Dataset 13", "data": [37, 27, 34] },
		{ "label": "Dataset 14", "data": [95, 79, 6] },
		{ "label": "Dataset 15", "data": [32, 34, 72] }
	]
}
